corva_assets/__init__.py
corva_assets/api_client.py
corva_assets/api_response.py
corva_assets/configuration.py
corva_assets/exceptions.py
corva_assets/py.typed
corva_assets/rest.py
corva_assets/api/__init__.py
corva_assets/api/assets_api.py
corva_assets/models/__init__.py
corva_assets/models/asset.py
corva_assets/models/asset_attributes.py
corva_assets/models/asset_attributes_source_well.py
corva_assets/models/assets.py
corva_assets/models/authentication_error.py
corva_assets/models/authorization_error.py
corva_assets/models/not_found_error.py
corva_assets-1.0.2.dist-info/METADATA
corva_assets-1.0.2.dist-info/WHEEL
corva_assets-1.0.2.dist-info/top_level.txt
corva_assets-1.0.2.dist-info/RECORD
