Metadata-Version: 2.1
Name: corva-assets
Version: 1.0.2
Summary: Corva Assets API Client
Home-page: 
Author: Tung Nguyen
Author-email: tungnq@gmail.com
Keywords: OpenAPI,OpenAPI-Generator,Corva Assets API
Requires-Dist: urllib3 <2.1.0,>=1.25.3
Requires-Dist: python-dateutil
Requires-Dist: pydantic <2,>=1.10.5
Requires-Dist: aenum
